easy_i18n/__init__.py
easy_i18n/t.py
easy_i18n-1.2.0.dist-info/LICENSE
easy_i18n-1.2.0.dist-info/METADATA
easy_i18n-1.2.0.dist-info/WHEEL
easy_i18n-1.2.0.dist-info/top_level.txt
easy_i18n-1.2.0.dist-info/RECORD
