Metadata-Version: 2.1
Name: easy-i18n
Version: 1.2.0
Summary: an easy way come true i18n for python3
Home-page: https://github.com/ALawating-Rex/easy_i18n
Author: aex
Author-email: aex.chen@qq.com
License: UNKNOWN
Platform: UNKNOWN
Classifier: Programming Language :: Python :: 3
Classifier: License :: OSI Approved :: MIT License
Classifier: Operating System :: OS Independent
